mdantic/__init__.py
mdantic/mdantic.py
mdantic/samples.py
markdown_mdantic-2.1.1.dist-info/LICENSE
markdown_mdantic-2.1.1.dist-info/METADATA
markdown_mdantic-2.1.1.dist-info/WHEEL
markdown_mdantic-2.1.1.dist-info/top_level.txt
markdown_mdantic-2.1.1.dist-info/RECORD
