Metadata-Version: 2.1
Name: markdown-mdantic
Version: 2.1.1
Summary: Python-Markdown extension for rendering pydantic BaseModel as table
Home-page: https://github.com/frefreak/mdantic
Author: Xiangyu Zhu
Author-email: frefreak.zxy@gmail.com
Classifier: Development Status :: 4 - Beta
Classifier: Intended Audience :: Developers
Classifier: Topic :: Text Processing :: Filters
Classifier: Topic :: Text Processing :: Markup :: HTML
Classifier: Programming Language :: Python :: 3.6
Classifier: Programming Language :: Python :: 3.7
Classifier: Programming Language :: Python :: 3.8
Classifier: Programming Language :: Python :: 3.9
Classifier: Programming Language :: Python :: 3.10
Classifier: Programming Language :: Python :: 3.11
License-File: LICENSE
Requires-Dist: markdown >=3.0
Requires-Dist: tabulate
Requires-Dist: pydantic >=2.0
